gb_f/.gb_f.py.swp
gb_f/__init__.py
gb_f/__main__.py
gb_f/data.json
gb_f/gb_f.py
gb_f/model.py
gb_f-0.0.0a0.dist-info/WHEEL
gb_f-0.0.0a0.dist-info/METADATA
gb_f-0.0.0a0.dist-info/RECORD
