Metadata-Version: 2.1
Name: gb_f
Version: 0.0.0a0
Summary: Governing Body Framework
Author: WK
Requires-Python: >=3.7
Classifier: Programming Language :: Python :: 3
Classifier: License :: OSI Approved :: BSD License
Classifier: Operating System :: OS Independent
